hiemal/__init__.py
hiemal-0.1.0a0.dist-info/LICENSE
hiemal-0.1.0a0.dist-info/METADATA
hiemal-0.1.0a0.dist-info/WHEEL
hiemal-0.1.0a0.dist-info/top_level.txt
hiemal-0.1.0a0.dist-info/RECORD
